{
    "Name": "Loki",
    "Quantity": 1,
    "Materials Used": {
        "Thermoelectric Catalysts": 7,
        "Jump Drive Control Nexus": 7,
        "Defensive Control Node": 7,
        "Central System Controller": 7,
        "Emergent Combat Intelligence": 7,
        "PPD Fullerene Fibers": 6,
        "Lanthanum Metallofullerene": 50,
        "C3-FTM Acid": 310,
        "Fullerene Intercalated Sheets": 8,
        "Metallofullerene Plating": 16,
        "Electromechanical Interface Nexus": 8,
        "Neurovisual Output Analyzer": 2,
        "Nanowire Composites": 21,
        "Fulleroferrocene Power Conduits": 3,
        "Superconducting Ladar Amplifier": 12,
        "R.A.M.- Starship Tech": 15
    }
}